my_krml_25763727/.DS_Store
my_krml_25763727/__init__.py
my_krml_25763727/data/.DS_Store
my_krml_25763727/data/sets.py
my_krml_25763727/features/.DS_Store
my_krml_25763727/features/dates.py
my_krml_25763727/models/.DS_Store
my_krml_25763727/models/null.py
my_krml_25763727/models/performance.py
dataset_merge-0.2.0.dist-info/METADATA
dataset_merge-0.2.0.dist-info/WHEEL
dataset_merge-0.2.0.dist-info/RECORD
