Metadata-Version: 2.3
Name: dataset-merge
Version: 0.2.0
Summary: Custom dataset merge, union and CSV utility
Author: Ananya
Author-email: anniesrinivas66@gmail.com
Requires-Python: >=3.11
Classifier: Programming Language :: Python :: 3
Classifier: Programming Language :: Python :: 3.11
Classifier: Programming Language :: Python :: 3.12
Classifier: Programming Language :: Python :: 3.13
Requires-Dist: pandas (>=1.5.0)
Project-URL: Homepage, https://github.com/An-nay/my_krml_25763727
